display/__init__.py
display/chart.py
display/layout.py
display/stack.py
stackviz/__init__.py
stackviz/display/__init__.py
stackviz/display/chart.py
stackviz/display/layout.py
stackviz/display/stack.py
stackviz/resources/default.css
stackviz/resources/echarts.min.js
stackviz/resources/template.tpl
stackviz-0.0.18.dist-info/LICENSE
stackviz-0.0.18.dist-info/METADATA
stackviz-0.0.18.dist-info/WHEEL
stackviz-0.0.18.dist-info/top_level.txt
stackviz-0.0.18.dist-info/RECORD
